power_api/__init__.py
power_api/command.py
power_api/definitions.py
power_api/event.py
power_api/exceptions.py
power_api/power_api.py
sixfab_power_python_api-0.2.2.dist-info/METADATA
sixfab_power_python_api-0.2.2.dist-info/WHEEL
sixfab_power_python_api-0.2.2.dist-info/top_level.txt
sixfab_power_python_api-0.2.2.dist-info/RECORD
