Metadata-Version: 2.1
Name: sixfab-power-python-api
Version: 0.2.2
Summary: Sixfab power management service python api
Home-page: https://github.com/sixfab/sixfab-power-python-api
Author: Yasin Kaya
Author-email: yasinkaya.121@gmail.com
License: MIT
Platform: UNKNOWN
Requires-Dist: crc16 (==0.1.1)
Requires-Dist: smbus2 (==0.3.0)
Requires-Dist: vcgencmd (==0.1.1)
